{
  "chapters": [
    {
      "id": "c1",
      "verses": [
        {
          "id": "c1v1",
          "text": "Павел, раб Иисуса Христа, призванный Апостол, избранный к благовестию Божию, ",
          "text_nasb": "Paul, a bond-servant of Christ Jesus, called as an apostle, set apart for the gospel of God,",
          "text_greek": [
            { "g": "Παῦλος", "r": "Павел", "t": "пАулос", "strong": 1401 },
            { "g": "δοῦλος", "r": "раб", "t": "дУлос", "strong": 1402 },
            { "g": "Χριστοῦ", "r": "Христа", "strong": 1403 },
            { "g": "’Ιησοῦ,", "r": "Иисуса,", "strong": 1404 },
            { "g": "κλητὸς", "r": "званый", "strong": 1405 },
            { "g": "ἀπόστολος,", "r": "апостол,", "strong": 1406 },
            { "g": "ἀφωρισμένος", "r": "отделённый", "strong": 1407 },
            { "g": "εἰς", "r": "в", "strong": 1408 },
            { "g": "εὐαγγέλιον", "r": "благовестие", "strong": 1409 },
            { "g": "θεοῦ,", "r": "Бога,", "strong": 1410 }
          ]
        },
        {
          "id": "c1v2",
          "text": "которое Бог прежде обещал через пророков Своих, в святых писаниях, ",
          "text_nasb": "which He promised beforehand through His prophets in the holy Scriptures,"
        },
        {
          "id": "c1v3",
          "text": "о Сыне Своем, Который родился от семени Давидова по плоти ",
          "text_nasb": "concerning His Son, who was born of a descendant of David according to the flesh,"
        },
        {
          "id": "c1v4",
          "text": "и открылся Сыном Божиим в силе, по духу святыни, через воскресение из мертвых, о Иисусе Христе, Господе нашем, ",
          "text_nasb": "who was declared the Son of God with power by the resurrection from the dead, according to the Spirit of holiness, Jesus Christ our Lord,"
        },
        {
          "text": "через Которого мы получили благодать и апостольство, чтобы во имя Его покорять вере все народы, ",
          "id": "c1v5"
        },
        {
          "text": "между которыми находитесь и вы, призванные Иисусом Христом, — ",
          "id": "c1v6"
        },
        {
          "text": "всем находящимся в Риме возлюбленным Божиим, призванным святым: благодать вам и мир от Бога Отца нашего и Господа Иисуса Христа.",
          "id": "c1v7"
        },
        {
          "text": "Прежде всего благодарю Бога моего через Иисуса Христа за всех вас, что вера ваша возвещается во всем мире. ",
          "id": "c1v8"
        },
        {
          "text": "Свидетель мне Бог, Которому служу духом моим в благовествовании Сына Его, что непрестанно воспоминаю о вас, ",
          "id": "c1v9"
        },
        {
          "text": "всегда прося в молитвах моих, чтобы воля Божия когда‐нибудь благопоспешила мне прийти к вам, ",
          "id": "c1v10"
        },
        {
          "text": "ибо я весьма желаю увидеть вас, чтобы преподать вам некое дарование духовное к утверждению вашему, ",
          "id": "c1v11"
        },
        {
          "text": "то есть утешиться с вами верою общею, вашею и моею.",
          "id": "c1v12"
        },
        {
          "text": "Не хочу, братия, оставить вас в неведении, что я многократно намеревался прийти к вам (но встречал препятствия даже доныне), чтобы иметь некий плод и у вас, как и у прочих народов. ",
          "id": "c1v13"
        },
        {
          "text": "Я должен и Еллинам и варварам, мудрецам и невеждам. ",
          "id": "c1v14"
        },
        {
          "text": "Итак, что до меня, я готов благовествовать и вам, находящимся в Риме. ",
          "id": "c1v15"
        },
        {
          "text": "Ибо я не стыжусь благовествования Христова, потому что оно есть сила Божия ко спасению всякому верующему, во‐первых, Иудею, потом и Еллину. ",
          "id": "c1v16"
        },
        {
          "text": "В нем открывается правда Божия от веры в веру, как написано: «праведный верою жив будет».",
          "id": "c1v17"
        },
        {
          "text": "Ибо открывается гнев Божий с неба на всякое нечестие и неправду человеков, подавляющих истину неправдою. ",
          "id": "c1v18"
        },
        {
          "text": "Ибо, что́ можно знать о Боге, явно для них, потому что Бог явил им. ",
          "id": "c1v19"
        },
        {
          "text": "Ибо невидимое Его, вечная сила Его и Божество, от создания мира через рассматривание творений видимы, так что они безответны. ",
          "id": "c1v20"
        },
        {
          "text": "Но как они, познав Бога, не прославили Его, как Бога, и не возблагодарили, но осуетились в умствованиях своих, и омрачилось несмысленное их сердце; ",
          "id": "c1v21"
        },
        {
          "text": "называя себя мудрыми, обезумели, ",
          "id": "c1v22"
        },
        {
          "text": "и славу нетленного Бога изменили в образ, подобный тленному человеку, и птицам, и четвероногим, и пресмыкающимся, — ",
          "id": "c1v23"
        },
        {
          "text": "то и предал их Бог в похотях сердец их нечистоте, так что они сквернили сами свои тела.",
          "id": "c1v24"
        },
        {
          "text": "Они заменили истину Божию ложью, и поклонялись, и служили твари вместо Творца, Который благословен вовеки, аминь. ",
          "id": "c1v25"
        },
        {
          "text": "Потому предал их Бог постыдным страстям: женщины их заменили естественное употребление противоестественным; ",
          "id": "c1v26"
        },
        {
          "text": "подобно и мужчины, оставив естественное употребление женского пола, разжигались похотью друг на друга, мужчины на мужчинах делая срам и получая в самих себе должное возмездие за свое заблуждение.",
          "id": "c1v27"
        },
        {
          "text": "И как они не заботились иметь Бога в разуме, то предал их Бог превратному уму — делать непотребства, ",
          "id": "c1v28"
        },
        {
          "text": "так что они исполнены всякой неправды, блуда, лукавства, корыстолюбия, злобы, исполнены зависти, убийства, распрей, обмана, злонравия, ",
          "id": "c1v29"
        },
        {
          "text": "злоречивы, клеветники, богоненавистники, обидчики, самохвалы, горды, изобретательны на зло, непослушны родителям, ",
          "id": "c1v30"
        },
        {
          "text": "безрассудны, вероломны, нелюбовны, непримиримы, немилостивы. ",
          "id": "c1v31"
        },
        {
          "text": "Они знают праведный суд Божий, что делающие такие дела достойны смерти; однако не только их делают, но и делающих одобряют.",
          "id": "c1v32"
        }
      ]
    }
  ]
}
